eldpy/__init__.py
eldpy/annotation.py
eldpy/archive.py
eldpy/bulk.py
eldpy/cldf2gb4e.py
eldpy/colexify.py
eldpy/collection.py
eldpy/constants.py
eldpy/delaman.py
eldpy/download.py
eldpy/elanfile.py
eldpy/lod.py
eldpy/paradisecconverter.py
eldpy/resolver.py
eldpy/testing.py
eldpy/transitiveclosure.py
eldpy/wikidatagraph.py
eldpy-0.0.12.dist-info/METADATA
eldpy-0.0.12.dist-info/WHEEL
eldpy-0.0.12.dist-info/RECORD
