Metadata-Version: 2.1
Name: eldpy
Version: 0.0.12
Summary: A Python package to download and analyze data from endangered language archives
Project-URL: Homepage, https://github.com/ZAS-QUEST/eldpy
Project-URL: Bug Tracker, https://github.com/ZAS-QUEST/eldpy/issues
Author-email: Sebastian Nordhoff <sebastian.nordhoff@glottotopia.de>
Classifier: License :: OSI Approved :: MIT License
Classifier: Operating System :: OS Independent
Classifier: Programming Language :: Python :: 3
Requires-Python: >=3.7
Requires-Dist: langdetect
Requires-Dist: lxml
Requires-Dist: matplotlib
Requires-Dist: pycryptodome
Requires-Dist: random2
Requires-Dist: rdflib
Requires-Dist: requests
Requires-Dist: wptools
Provides-Extra: dev
